connection_server/__init__.py
connection_server/connect_tcp.py
connection_server/connect_udp.py
connection_server-0.0.1.dist-info/METADATA
connection_server-0.0.1.dist-info/WHEEL
connection_server-0.0.1.dist-info/top_level.txt
connection_server-0.0.1.dist-info/RECORD
