Metadata-Version: 2.1
Name: connection-server
Version: 0.0.1
Summary: My short description
Home-page: https://github.com/Konstructa/my-package-python
Author: milena_limoeiro
Author-email: elenprojects7@gmail.com
License: UNKNOWN
Platform: UNKNOWN
Requires-Python: >=3.8
